stackweaver/__init__.py
stackweaver/cli/__init__.py
stackweaver/cli/commands/__init__.py
stackweaver/cli/commands/deploy.py
stackweaver/cli/commands/init.py
stackweaver/cli/commands/logs.py
stackweaver/cli/commands/rollback.py
stackweaver/cli/commands/search.py
stackweaver/cli/commands/secrets.py
stackweaver/cli/commands/start.py
stackweaver/cli/commands/status.py
stackweaver/cli/commands/stop.py
stackweaver/cli/main.py
stackweaver/cli/ui_helpers.py
stackweaver/core/__init__.py
stackweaver/core/agents/__init__.py
stackweaver/core/agents/architect.py
stackweaver/core/agents/curator.py
stackweaver/core/errors.py
stackweaver/core/resources.py
stackweaver/core/stackweaver_core.py
stackweaver/core/state_manager.py
stackweaver/deployer/__init__.py
stackweaver/deployer/docker_client.py
stackweaver/deployer/docker_deployer.py
stackweaver/generator/__init__.py
stackweaver/generator/isolation.py
stackweaver/generator/secrets.py
stackweaver/generator/templates/docker-compose.j2
stackweaver/generator/templates/service.j2
stackweaver/generator/templates/traefik.j2
stackweaver/generator/validators.py
stackweaver/generator/volumes.py
stackweaver/generator/yaml_generator.py
stackweaver/knowledge_base/__init__.py
stackweaver/knowledge_base/tools_index.json
stackweaver/search/__init__.py
stackweaver/search/ingest.py
stackweaver/search/llm_ranker.py
stackweaver/search/schemas.py
stackweaver/search/tool_search.py
stackweaver/search/vector_store.py
stackweaver/utils/__init__.py
stackweaver/utils/config_loader.py
stackweaver/utils/logger.py
stackweaver-0.1.3.dist-info/METADATA
stackweaver-0.1.3.dist-info/WHEEL
stackweaver-0.1.3.dist-info/entry_points.txt
stackweaver-0.1.3.dist-info/licenses/LICENSE
stackweaver-0.1.3.dist-info/RECORD
