Metadata-Version: 2.4
Name: stackweaver
Version: 0.1.3
Summary: The Autonomous System Integrator - AI-powered Docker orchestration
License: MIT
License-File: LICENSE
Keywords: docker,orchestration,ai,devops,automation,docker-compose,cli,traefik,infrastructure
Author: Ahmed
Author-email: ahmed.b.daamer@gmail.com
Requires-Python: >=3.11,<4.0
Classifier: Development Status :: 4 - Beta
Classifier: Intended Audience :: Developers
Classifier: Intended Audience :: System Administrators
Classifier: License :: OSI Approved :: MIT License
Classifier: Operating System :: OS Independent
Classifier: Programming Language :: Python :: 3
Classifier: Programming Language :: Python :: 3.11
Classifier: Programming Language :: Python :: 3.12
Classifier: Programming Language :: Python :: 3.13
Classifier: Programming Language :: Python :: 3.14
Classifier: Topic :: Software Development :: Build Tools
Classifier: Topic :: System :: Systems Administration
Classifier: Topic :: Utilities
Requires-Dist: chromadb (>=0.4.22,<0.5.0)
Requires-Dist: click (>=8.1.7,<9.0.0)
Requires-Dist: docker (>=7.0.0,<8.0.0)
Requires-Dist: httpx (>=0.26.0,<0.27.0)
Requires-Dist: jinja2 (>=3.1.3,<4.0.0)
Requires-Dist: litellm (>=1.17.0,<2.0.0)
Requires-Dist: numpy (<2.0)
Requires-Dist: pydantic (>=2.5.3,<3.0.0)
Requires-Dist: python-dotenv (>=1.0.0,<2.0.0)
Requires-Dist: python-on-whales (>=0.69.0,<0.70.0)
Requires-Dist: pyyaml (>=6.0.1,<7.0.0)
Requires-Dist: rich (>=13.7.0,<14.0.0)
Project-URL: Documentation, https://github.com/stackweaver-io/stackweaver#readme
Project-URL: Homepage, https://github.com/stackweaver-io/stackweaver
Project-URL: Repository, https://github.com/stackweaver-io/stackweaver
